{
  "type": "FeatureCollection",
  "properties": {
  },
  "features": [
    {
      "type": "Feature",
      "geometry": {
        "type": "Point",
        "coordinates": [16.3250000000, 48.0000000000]
      },
      "properties": {
        "deg": "2",
        "deg_in": "2",
        "deg_out": "2",
        "id": "0x5634717e3250",
        "station_id": "(1, 10)",
        "station_label": "(1, 10)"
      }
    }, 
    {
      "type": "Feature",
      "geometry": {
        "type": "Point",
        "coordinates": [16.3500000000, 48.1000000000]
      },
      "properties": {
        "deg": "3",
        "deg_in": "3",
        "deg_out": "3",
        "id": "0x56347184ff10",
        "station_id": "(2, 6)",
        "station_label": "(2, 6)"
      }
    }, 
    {
      "type": "Feature",
      "geometry": {
        "type": "Point",
        "coordinates": [16.3750000000, 47.8500000000]
      },
      "properties": {
        "deg": "1",
        "deg_in": "1",
        "deg_out": "1",
        "id": "0x563471850100",
        "station_id": "(3, 16)",
        "station_label": "(3, 16)"
      }
    }, 
    {
      "type": "Feature",
      "geometry": {
        "type": "Point",
        "coordinates": [16.4000000000, 48.2000000000]
      },
      "properties": {
        "deg": "2",
        "deg_in": "2",
        "deg_out": "2",
        "id": "0x5634718502f0",
        "station_id": "(4, 2)",
        "station_label": "(4, 2)"
      }
    }, 
    {
      "type": "Feature",
      "geometry": {
        "type": "Point",
        "coordinates": [16.4000000000, 48.1250000000]
      },
      "properties": {
        "deg": "2",
        "deg_in": "2",
        "deg_out": "2",
        "id": "0x5634718504e0",
        "station_id": "(4, 5)",
        "station_label": "(4, 5)"
      }
    }, 
    {
      "type": "Feature",
      "geometry": {
        "type": "Point",
        "coordinates": [16.4250000000, 48.2250000000]
      },
      "properties": {
        "deg": "2",
        "deg_in": "2",
        "deg_out": "2",
        "id": "0x5634718506d0",
        "station_id": "(5, 1)",
        "station_label": "(5, 1)"
      }
    }, 
    {
      "type": "Feature",
      "geometry": {
        "type": "Point",
        "coordinates": [16.4500000000, 47.9750000000]
      },
      "properties": {
        "deg": "1",
        "deg_in": "1",
        "deg_out": "1",
        "id": "0x5634718508c0",
        "station_id": "(6, 11)",
        "station_label": "(6, 11)"
      }
    }, 
    {
      "type": "Feature",
      "geometry": {
        "type": "Point",
        "coordinates": [16.4750000000, 48.0250000000]
      },
      "properties": {
        "deg": "4",
        "deg_in": "4",
        "deg_out": "4",
        "id": "0x563471850ab0",
        "station_id": "(7, 9)",
        "station_label": "(7, 9)"
      }
    }, 
    {
      "type": "Feature",
      "geometry": {
        "type": "Point",
        "coordinates": [16.5250000000, 47.8750000000]
      },
      "properties": {
        "deg": "2",
        "deg_in": "2",
        "deg_out": "2",
        "id": "0x563471850ca0",
        "station_id": "(9, 15)",
        "station_label": "(9, 15)"
      }
    }, 
    {
      "type": "Feature",
      "geometry": {
        "type": "Point",
        "coordinates": [16.5500000000, 48.1500000000]
      },
      "properties": {
        "deg": "2",
        "deg_in": "2",
        "deg_out": "2",
        "id": "0x563471850e90",
        "station_id": "(10, 4)",
        "station_label": "(10, 4)"
      }
    }, 
    {
      "type": "Feature",
      "geometry": {
        "type": "Point",
        "coordinates": [16.5500000000, 47.9250000000]
      },
      "properties": {
        "deg": "2",
        "deg_in": "2",
        "deg_out": "2",
        "id": "0x563471851080",
        "station_id": "(10, 13)",
        "station_label": "(10, 13)"
      }
    }, 
    {
      "type": "Feature",
      "geometry": {
        "type": "Point",
        "coordinates": [16.5500000000, 47.9000000000]
      },
      "properties": {
        "deg": "2",
        "deg_in": "2",
        "deg_out": "2",
        "id": "0x563471851270",
        "station_id": "(10, 14)",
        "station_label": "(10, 14)"
      }
    }, 
    {
      "type": "Feature",
      "geometry": {
        "type": "Point",
        "coordinates": [16.5750000000, 48.1250000000]
      },
      "properties": {
        "deg": "3",
        "deg_in": "3",
        "deg_out": "3",
        "id": "0x563471851460",
        "station_id": "(11, 5)",
        "station_label": "(11, 5)"
      }
    }, 
    {
      "type": "Feature",
      "geometry": {
        "type": "Point",
        "coordinates": [16.5750000000, 47.9250000000]
      },
      "properties": {
        "deg": "2",
        "deg_in": "2",
        "deg_out": "2",
        "id": "0x563471851650",
        "station_id": "(11, 13)",
        "station_label": "(11, 13)"
      }
    }, 
    {
      "type": "Feature",
      "geometry": {
        "type": "Point",
        "coordinates": [16.6250000000, 48.0500000000]
      },
      "properties": {
        "deg": "4",
        "deg_in": "4",
        "deg_out": "4",
        "id": "0x563471851840",
        "station_id": "(13, 8)",
        "station_label": "(13, 8)"
      }
    }, 
    {
      "type": "Feature",
      "geometry": {
        "type": "Point",
        "coordinates": [16.6500000000, 47.9250000000]
      },
      "properties": {
        "deg": "2",
        "deg_in": "2",
        "deg_out": "2",
        "id": "0x563471851a30",
        "station_id": "(14, 13)",
        "station_label": "(14, 13)"
      }
    }, 
    {
      "type": "Feature",
      "geometry": {
        "type": "Point",
        "coordinates": [16.6500000000, 47.8500000000]
      },
      "properties": {
        "deg": "2",
        "deg_in": "2",
        "deg_out": "2",
        "id": "0x563471851c20",
        "station_id": "(14, 16)",
        "station_label": "(14, 16)"
      }
    }, 
    {
      "type": "Feature",
      "geometry": {
        "type": "Point",
        "coordinates": [16.6750000000, 48.1750000000]
      },
      "properties": {
        "deg": "2",
        "deg_in": "2",
        "deg_out": "2",
        "id": "0x563471851e10",
        "station_id": "(15, 3)",
        "station_label": "(15, 3)"
      }
    }, 
    {
      "type": "Feature",
      "geometry": {
        "type": "Point",
        "coordinates": [16.7000000000, 48.1750000000]
      },
      "properties": {
        "deg": "1",
        "deg_in": "1",
        "deg_out": "1",
        "id": "0x563471852000",
        "station_id": "(16, 3)",
        "station_label": "(16, 3)"
      }
    }, 
    {
      "type": "Feature",
      "geometry": {
        "type": "Point",
        "coordinates": [16.7000000000, 47.9750000000]
      },
      "properties": {
        "deg": "2",
        "deg_in": "2",
        "deg_out": "2",
        "id": "0x5634718521f0",
        "station_id": "(16, 11)",
        "station_label": "(16, 11)"
      }
    }, 
    {
      "type": "Feature",
      "geometry": {
        "type": "Point",
        "coordinates": [16.3250000000, 48.0750000000]
      },
      "properties": {
        "deg": "2",
        "deg_in": "2",
        "deg_out": "2",
        "id": "0x5634718523e0",
        "station_id": "(1, 7)",
        "station_label": "(1, 7)"
      }
    }, 
    {
      "type": "Feature",
      "geometry": {
        "type": "Point",
        "coordinates": [16.3250000000, 48.0500000000]
      },
      "properties": {
        "deg": "2",
        "deg_in": "2",
        "deg_out": "2",
        "id": "0x5634718525d0",
        "station_id": "(1, 8)",
        "station_label": "(1, 8)"
      }
    }, 
    {
      "type": "Feature",
      "geometry": {
        "type": "Point",
        "coordinates": [16.3250000000, 48.0250000000]
      },
      "properties": {
        "deg": "2",
        "deg_in": "2",
        "deg_out": "2",
        "id": "0x5634718527c0",
        "station_id": "(1, 9)",
        "station_label": "(1, 9)"
      }
    }, 
    {
      "type": "Feature",
      "geometry": {
        "type": "Point",
        "coordinates": [16.3500000000, 48.0250000000]
      },
      "properties": {
        "deg": "2",
        "deg_in": "2",
        "deg_out": "2",
        "id": "0x5634718529b0",
        "station_id": "(2, 9)",
        "station_label": "(2, 9)"
      }
    }, 
    {
      "type": "Feature",
      "geometry": {
        "type": "Point",
        "coordinates": [16.3750000000, 48.1000000000]
      },
      "properties": {
        "deg": "2",
        "deg_in": "2",
        "deg_out": "2",
        "id": "0x563471852ba0",
        "station_id": "(3, 6)",
        "station_label": "(3, 6)"
      }
    }, 
    {
      "type": "Feature",
      "geometry": {
        "type": "Point",
        "coordinates": [16.3750000000, 48.0750000000]
      },
      "properties": {
        "deg": "2",
        "deg_in": "2",
        "deg_out": "2",
        "id": "0x563471852d90",
        "station_id": "(3, 7)",
        "station_label": "(3, 7)"
      }
    }, 
    {
      "type": "Feature",
      "geometry": {
        "type": "Point",
        "coordinates": [16.3750000000, 48.0250000000]
      },
      "properties": {
        "deg": "2",
        "deg_in": "2",
        "deg_out": "2",
        "id": "0x563471852f80",
        "station_id": "(3, 9)",
        "station_label": "(3, 9)"
      }
    }, 
    {
      "type": "Feature",
      "geometry": {
        "type": "Point",
        "coordinates": [16.4000000000, 48.0500000000]
      },
      "properties": {
        "deg": "2",
        "deg_in": "2",
        "deg_out": "2",
        "id": "0x563471853170",
        "station_id": "(4, 8)",
        "station_label": "(4, 8)"
      }
    }, 
    {
      "type": "Feature",
      "geometry": {
        "type": "Point",
        "coordinates": [16.4000000000, 48.0250000000]
      },
      "properties": {
        "deg": "2",
        "deg_in": "2",
        "deg_out": "2",
        "id": "0x563471853360",
        "station_id": "(4, 9)",
        "station_label": "(4, 9)"
      }
    }, 
    {
      "type": "Feature",
      "geometry": {
        "type": "Point",
        "coordinates": [16.4000000000, 47.8750000000]
      },
      "properties": {
        "deg": "2",
        "deg_in": "2",
        "deg_out": "2",
        "id": "0x563471853550",
        "station_id": "(4, 15)",
        "station_label": "(4, 15)"
      }
    }, 
    {
      "type": "Feature",
      "geometry": {
        "type": "Point",
        "coordinates": [16.4000000000, 48.1750000000]
      },
      "properties": {
        "deg": "2",
        "deg_in": "2",
        "deg_out": "2",
        "id": "0x563471853740",
        "station_id": "(4, 3)",
        "station_label": "(4, 3)"
      }
    }, 
    {
      "type": "Feature",
      "geometry": {
        "type": "Point",
        "coordinates": [16.4000000000, 48.1500000000]
      },
      "properties": {
        "deg": "2",
        "deg_in": "2",
        "deg_out": "2",
        "id": "0x563471853930",
        "station_id": "(4, 4)",
        "station_label": "(4, 4)"
      }
    }, 
    {
      "type": "Feature",
      "geometry": {
        "type": "Point",
        "coordinates": [16.4250000000, 48.0250000000]
      },
      "properties": {
        "deg": "3",
        "deg_in": "3",
        "deg_out": "3",
        "id": "0x563471853b20",
        "station_id": "(5, 9)",
        "station_label": "(5, 9)"
      }
    }, 
    {
      "type": "Feature",
      "geometry": {
        "type": "Point",
        "coordinates": [16.4250000000, 47.9000000000]
      },
      "properties": {
        "deg": "2",
        "deg_in": "2",
        "deg_out": "2",
        "id": "0x563471853d10",
        "station_id": "(5, 14)",
        "station_label": "(5, 14)"
      }
    }, 
    {
      "type": "Feature",
      "geometry": {
        "type": "Point",
        "coordinates": [16.4500000000, 48.2250000000]
      },
      "properties": {
        "deg": "2",
        "deg_in": "2",
        "deg_out": "2",
        "id": "0x563471853f00",
        "station_id": "(6, 1)",
        "station_label": "(6, 1)"
      }
    }, 
    {
      "type": "Feature",
      "geometry": {
        "type": "Point",
        "coordinates": [16.4500000000, 48.0250000000]
      },
      "properties": {
        "deg": "2",
        "deg_in": "2",
        "deg_out": "2",
        "id": "0x5634718540f0",
        "station_id": "(6, 9)",
        "station_label": "(6, 9)"
      }
    }, 
    {
      "type": "Feature",
      "geometry": {
        "type": "Point",
        "coordinates": [16.4500000000, 47.9250000000]
      },
      "properties": {
        "deg": "2",
        "deg_in": "2",
        "deg_out": "2",
        "id": "0x5634718542e0",
        "station_id": "(6, 13)",
        "station_label": "(6, 13)"
      }
    }, 
    {
      "type": "Feature",
      "geometry": {
        "type": "Point",
        "coordinates": [16.4750000000, 48.2250000000]
      },
      "properties": {
        "deg": "2",
        "deg_in": "2",
        "deg_out": "2",
        "id": "0x5634718544d0",
        "station_id": "(7, 1)",
        "station_label": "(7, 1)"
      }
    }, 
    {
      "type": "Feature",
      "geometry": {
        "type": "Point",
        "coordinates": [16.4750000000, 48.0000000000]
      },
      "properties": {
        "deg": "2",
        "deg_in": "2",
        "deg_out": "2",
        "id": "0x5634718546c0",
        "station_id": "(7, 10)",
        "station_label": "(7, 10)"
      }
    }, 
    {
      "type": "Feature",
      "geometry": {
        "type": "Point",
        "coordinates": [16.4750000000, 47.9500000000]
      },
      "properties": {
        "deg": "2",
        "deg_in": "2",
        "deg_out": "2",
        "id": "0x5634718548b0",
        "station_id": "(7, 12)",
        "station_label": "(7, 12)"
      }
    }, 
    {
      "type": "Feature",
      "geometry": {
        "type": "Point",
        "coordinates": [16.5000000000, 48.2000000000]
      },
      "properties": {
        "deg": "2",
        "deg_in": "2",
        "deg_out": "2",
        "id": "0x563471854aa0",
        "station_id": "(8, 2)",
        "station_label": "(8, 2)"
      }
    }, 
    {
      "type": "Feature",
      "geometry": {
        "type": "Point",
        "coordinates": [16.5000000000, 48.0250000000]
      },
      "properties": {
        "deg": "2",
        "deg_in": "2",
        "deg_out": "2",
        "id": "0x563471854c90",
        "station_id": "(8, 9)",
        "station_label": "(8, 9)"
      }
    }, 
    {
      "type": "Feature",
      "geometry": {
        "type": "Point",
        "coordinates": [16.5000000000, 48.0000000000]
      },
      "properties": {
        "deg": "2",
        "deg_in": "2",
        "deg_out": "2",
        "id": "0x563471854e80",
        "station_id": "(8, 10)",
        "station_label": "(8, 10)"
      }
    }, 
    {
      "type": "Feature",
      "geometry": {
        "type": "Point",
        "coordinates": [16.5000000000, 47.9750000000]
      },
      "properties": {
        "deg": "2",
        "deg_in": "2",
        "deg_out": "2",
        "id": "0x563471855070",
        "station_id": "(8, 11)",
        "station_label": "(8, 11)"
      }
    }, 
    {
      "type": "Feature",
      "geometry": {
        "type": "Point",
        "coordinates": [16.5250000000, 48.1750000000]
      },
      "properties": {
        "deg": "2",
        "deg_in": "2",
        "deg_out": "2",
        "id": "0x563471855260",
        "station_id": "(9, 3)",
        "station_label": "(9, 3)"
      }
    }, 
    {
      "type": "Feature",
      "geometry": {
        "type": "Point",
        "coordinates": [16.5250000000, 48.0250000000]
      },
      "properties": {
        "deg": "2",
        "deg_in": "2",
        "deg_out": "2",
        "id": "0x563471855450",
        "station_id": "(9, 9)",
        "station_label": "(9, 9)"
      }
    }, 
    {
      "type": "Feature",
      "geometry": {
        "type": "Point",
        "coordinates": [16.5250000000, 47.9750000000]
      },
      "properties": {
        "deg": "2",
        "deg_in": "2",
        "deg_out": "2",
        "id": "0x563471855640",
        "station_id": "(9, 11)",
        "station_label": "(9, 11)"
      }
    }, 
    {
      "type": "Feature",
      "geometry": {
        "type": "Point",
        "coordinates": [16.5250000000, 48.0000000000]
      },
      "properties": {
        "deg": "2",
        "deg_in": "2",
        "deg_out": "2",
        "id": "0x563471855830",
        "station_id": "(9, 10)",
        "station_label": "(9, 10)"
      }
    }, 
    {
      "type": "Feature",
      "geometry": {
        "type": "Point",
        "coordinates": [16.5500000000, 48.0250000000]
      },
      "properties": {
        "deg": "4",
        "deg_in": "4",
        "deg_out": "4",
        "id": "0x563471855a20",
        "station_id": "(10, 9)",
        "station_label": "(10, 9)"
      }
    }, 
    {
      "type": "Feature",
      "geometry": {
        "type": "Point",
        "coordinates": [16.5500000000, 47.9500000000]
      },
      "properties": {
        "deg": "2",
        "deg_in": "2",
        "deg_out": "2",
        "id": "0x563471855c10",
        "station_id": "(10, 12)",
        "station_label": "(10, 12)"
      }
    }, 
    {
      "type": "Feature",
      "geometry": {
        "type": "Point",
        "coordinates": [16.5500000000, 47.8500000000]
      },
      "properties": {
        "deg": "2",
        "deg_in": "2",
        "deg_out": "2",
        "id": "0x563471855e00",
        "station_id": "(10, 16)",
        "station_label": "(10, 16)"
      }
    }, 
    {
      "type": "Feature",
      "geometry": {
        "type": "Point",
        "coordinates": [16.5750000000, 48.0500000000]
      },
      "properties": {
        "deg": "2",
        "deg_in": "2",
        "deg_out": "2",
        "id": "0x563471855ff0",
        "station_id": "(11, 8)",
        "station_label": "(11, 8)"
      }
    }, 
    {
      "type": "Feature",
      "geometry": {
        "type": "Point",
        "coordinates": [16.5750000000, 48.0250000000]
      },
      "properties": {
        "deg": "2",
        "deg_in": "2",
        "deg_out": "2",
        "id": "0x5634718561e0",
        "station_id": "(11, 9)",
        "station_label": "(11, 9)"
      }
    }, 
    {
      "type": "Feature",
      "geometry": {
        "type": "Point",
        "coordinates": [16.5750000000, 47.8500000000]
      },
      "properties": {
        "deg": "2",
        "deg_in": "2",
        "deg_out": "2",
        "id": "0x5634718563d0",
        "station_id": "(11, 16)",
        "station_label": "(11, 16)"
      }
    }, 
    {
      "type": "Feature",
      "geometry": {
        "type": "Point",
        "coordinates": [16.6000000000, 48.1500000000]
      },
      "properties": {
        "deg": "2",
        "deg_in": "2",
        "deg_out": "2",
        "id": "0x5634718565c0",
        "station_id": "(12, 4)",
        "station_label": "(12, 4)"
      }
    }, 
    {
      "type": "Feature",
      "geometry": {
        "type": "Point",
        "coordinates": [16.6000000000, 48.1000000000]
      },
      "properties": {
        "deg": "2",
        "deg_in": "2",
        "deg_out": "2",
        "id": "0x5634718567b0",
        "station_id": "(12, 6)",
        "station_label": "(12, 6)"
      }
    }, 
    {
      "type": "Feature",
      "geometry": {
        "type": "Point",
        "coordinates": [16.6000000000, 48.0500000000]
      },
      "properties": {
        "deg": "2",
        "deg_in": "2",
        "deg_out": "2",
        "id": "0x5634718569a0",
        "station_id": "(12, 8)",
        "station_label": "(12, 8)"
      }
    }, 
    {
      "type": "Feature",
      "geometry": {
        "type": "Point",
        "coordinates": [16.6000000000, 48.0250000000]
      },
      "properties": {
        "deg": "2",
        "deg_in": "2",
        "deg_out": "2",
        "id": "0x563471856b90",
        "station_id": "(12, 9)",
        "station_label": "(12, 9)"
      }
    }, 
    {
      "type": "Feature",
      "geometry": {
        "type": "Point",
        "coordinates": [16.6000000000, 47.8500000000]
      },
      "properties": {
        "deg": "2",
        "deg_in": "2",
        "deg_out": "2",
        "id": "0x563471856d80",
        "station_id": "(12, 16)",
        "station_label": "(12, 16)"
      }
    }, 
    {
      "type": "Feature",
      "geometry": {
        "type": "Point",
        "coordinates": [16.6250000000, 48.1750000000]
      },
      "properties": {
        "deg": "2",
        "deg_in": "2",
        "deg_out": "2",
        "id": "0x563471856f70",
        "station_id": "(13, 3)",
        "station_label": "(13, 3)"
      }
    }, 
    {
      "type": "Feature",
      "geometry": {
        "type": "Point",
        "coordinates": [16.6250000000, 48.0750000000]
      },
      "properties": {
        "deg": "2",
        "deg_in": "2",
        "deg_out": "2",
        "id": "0x563471857160",
        "station_id": "(13, 7)",
        "station_label": "(13, 7)"
      }
    }, 
    {
      "type": "Feature",
      "geometry": {
        "type": "Point",
        "coordinates": [16.6250000000, 47.8500000000]
      },
      "properties": {
        "deg": "2",
        "deg_in": "2",
        "deg_out": "2",
        "id": "0x563471857350",
        "station_id": "(13, 16)",
        "station_label": "(13, 16)"
      }
    }, 
    {
      "type": "Feature",
      "geometry": {
        "type": "Point",
        "coordinates": [16.6500000000, 48.1750000000]
      },
      "properties": {
        "deg": "2",
        "deg_in": "2",
        "deg_out": "2",
        "id": "0x563471857540",
        "station_id": "(14, 3)",
        "station_label": "(14, 3)"
      }
    }, 
    {
      "type": "Feature",
      "geometry": {
        "type": "Point",
        "coordinates": [16.6500000000, 48.0250000000]
      },
      "properties": {
        "deg": "2",
        "deg_in": "2",
        "deg_out": "2",
        "id": "0x563471857730",
        "station_id": "(14, 9)",
        "station_label": "(14, 9)"
      }
    }, 
    {
      "type": "Feature",
      "geometry": {
        "type": "Point",
        "coordinates": [16.6750000000, 48.0000000000]
      },
      "properties": {
        "deg": "2",
        "deg_in": "2",
        "deg_out": "2",
        "id": "0x563471857920",
        "station_id": "(15, 10)",
        "station_label": "(15, 10)"
      }
    }, 
    {
      "type": "Feature",
      "geometry": {
        "type": "Point",
        "coordinates": [16.6750000000, 47.9500000000]
      },
      "properties": {
        "deg": "2",
        "deg_in": "2",
        "deg_out": "2",
        "id": "0x563471857b10",
        "station_id": "(15, 12)",
        "station_label": "(15, 12)"
      }
    }, 
    {
      "type": "Feature",
      "geometry": {
        "type": "Point",
        "coordinates": [16.6500000000, 47.9000000000]
      },
      "properties": {
        "deg": "2",
        "deg_in": "2",
        "deg_out": "2",
        "id": "0x563471857d00",
        "station_id": "(14, 14)",
        "station_label": "(14, 14)"
      }
    }, 
    {
      "type": "Feature",
      "geometry": {
        "type": "Point",
        "coordinates": [16.6500000000, 47.8750000000]
      },
      "properties": {
        "deg": "2",
        "deg_in": "2",
        "deg_out": "2",
        "id": "0x563471857ef0",
        "station_id": "(14, 15)",
        "station_label": "(14, 15)"
      }
    }, 
    {
      "type": "Feature",
      "geometry": {
        "type": "LineString",
        "coordinates": [[16.3250000000, 48.0000000000], [16.3250000000, 48.0250000000]]
      },
      "properties": {
        "dbg_lines": "S3",
        "from": "0x5634717e3250",
        "id": "0x5634717e1dc0",
        "lines": [
          {
            "color": "",
            "id": "S3",
            "label": "S3"
          }],
        "to": "0x5634718527c0"
      }
    }, 
    {
      "type": "Feature",
      "geometry": {
        "type": "LineString",
        "coordinates": [[16.3250000000, 48.0000000000], [16.3500000000, 48.0250000000]]
      },
      "properties": {
        "dbg_lines": "S3,S2",
        "from": "0x5634717e3250",
        "id": "0x563471858da0",
        "lines": [
          {
            "color": "",
            "id": "S3",
            "label": "S3"
          }, 
          {
            "color": "",
            "id": "S2",
            "label": "S2"
          }],
        "to": "0x5634718529b0"
      }
    }, 
    {
      "type": "Feature",
      "geometry": {
        "type": "LineString",
        "coordinates": [[16.3500000000, 48.1000000000], [16.3250000000, 48.0750000000]]
      },
      "properties": {
        "dbg_lines": "S3",
        "from": "0x56347184ff10",
        "id": "0x563471859590",
        "lines": [
          {
            "color": "",
            "id": "S3",
            "label": "S3"
          }],
        "to": "0x5634718523e0"
      }
    }, 
    {
      "type": "Feature",
      "geometry": {
        "type": "LineString",
        "coordinates": [[16.3500000000, 48.1000000000], [16.3750000000, 48.1000000000]]
      },
      "properties": {
        "dbg_lines": "S3",
        "from": "0x56347184ff10",
        "id": "0x563471859710",
        "lines": [
          {
            "color": "",
            "id": "S3",
            "label": "S3"
          }],
        "to": "0x563471852ba0"
      }
    }, 
    {
      "type": "Feature",
      "geometry": {
        "type": "LineString",
        "coordinates": [[16.3500000000, 48.1000000000], [16.3750000000, 48.0750000000]]
      },
      "properties": {
        "dbg_lines": "S1",
        "from": "0x56347184ff10",
        "id": "0x563471859850",
        "lines": [
          {
            "color": "",
            "id": "S1",
            "label": "S1"
          }],
        "to": "0x563471852d90"
      }
    }, 
    {
      "type": "Feature",
      "geometry": {
        "type": "LineString",
        "coordinates": [[16.3750000000, 47.8500000000], [16.4000000000, 47.8750000000]]
      },
      "properties": {
        "dbg_lines": "S5",
        "from": "0x563471850100",
        "id": "0x563471859a50",
        "lines": [
          {
            "color": "",
            "id": "S5",
            "label": "S5"
          }],
        "to": "0x563471853550"
      }
    }, 
    {
      "type": "Feature",
      "geometry": {
        "type": "LineString",
        "coordinates": [[16.4000000000, 48.2000000000], [16.4250000000, 48.2250000000]]
      },
      "properties": {
        "dbg_lines": "S3",
        "from": "0x5634718502f0",
        "id": "0x563471859c70",
        "lines": [
          {
            "color": "",
            "id": "S3",
            "label": "S3"
          }],
        "to": "0x5634718506d0"
      }
    }, 
    {
      "type": "Feature",
      "geometry": {
        "type": "LineString",
        "coordinates": [[16.4000000000, 48.2000000000], [16.4000000000, 48.1750000000]]
      },
      "properties": {
        "dbg_lines": "S3",
        "from": "0x5634718502f0",
        "id": "0x563471859dd0",
        "lines": [
          {
            "color": "",
            "id": "S3",
            "label": "S3"
          }],
        "to": "0x563471853740"
      }
    }, 
    {
      "type": "Feature",
      "geometry": {
        "type": "LineString",
        "coordinates": [[16.4000000000, 48.1250000000], [16.3750000000, 48.1000000000]]
      },
      "properties": {
        "dbg_lines": "S3",
        "from": "0x5634718504e0",
        "id": "0x563471859f10",
        "lines": [
          {
            "color": "",
            "id": "S3",
            "label": "S3"
          }],
        "to": "0x563471852ba0"
      }
    }, 
    {
      "type": "Feature",
      "geometry": {
        "type": "LineString",
        "coordinates": [[16.4000000000, 48.1250000000], [16.4000000000, 48.1500000000]]
      },
      "properties": {
        "dbg_lines": "S3",
        "from": "0x5634718504e0",
        "id": "0x56347185a050",
        "lines": [
          {
            "color": "",
            "id": "S3",
            "label": "S3"
          }],
        "to": "0x563471853930"
      }
    }, 
    {
      "type": "Feature",
      "geometry": {
        "type": "LineString",
        "coordinates": [[16.4250000000, 48.2250000000], [16.4500000000, 48.2250000000]]
      },
      "properties": {
        "dbg_lines": "S3",
        "from": "0x5634718506d0",
        "id": "0x56347185a1f0",
        "lines": [
          {
            "color": "",
            "id": "S3",
            "label": "S3"
          }],
        "to": "0x563471853f00"
      }
    }, 
    {
      "type": "Feature",
      "geometry": {
        "type": "LineString",
        "coordinates": [[16.4500000000, 47.9750000000], [16.4750000000, 48.0000000000]]
      },
      "properties": {
        "dbg_lines": "S4,S3",
        "from": "0x5634718508c0",
        "id": "0x56347185a390",
        "lines": [
          {
            "color": "",
            "id": "S4",
            "label": "S4"
          }, 
          {
            "color": "",
            "id": "S3",
            "label": "S3"
          }],
        "to": "0x5634718546c0"
      }
    }, 
    {
      "type": "Feature",
      "geometry": {
        "type": "LineString",
        "coordinates": [[16.4750000000, 48.0250000000], [16.4500000000, 48.0250000000]]
      },
      "properties": {
        "dbg_lines": "S1,S2,S3",
        "from": "0x563471850ab0",
        "id": "0x56347185aaf0",
        "lines": [
          {
            "color": "",
            "id": "S1",
            "label": "S1"
          }, 
          {
            "color": "",
            "id": "S2",
            "label": "S2"
          }, 
          {
            "color": "",
            "id": "S3",
            "label": "S3"
          }],
        "to": "0x5634718540f0"
      }
    }, 
    {
      "type": "Feature",
      "geometry": {
        "type": "LineString",
        "coordinates": [[16.4750000000, 48.0250000000], [16.5000000000, 48.0250000000]]
      },
      "properties": {
        "dbg_lines": "S1",
        "from": "0x563471850ab0",
        "id": "0x56347185b340",
        "lines": [
          {
            "color": "",
            "id": "S1",
            "label": "S1"
          }],
        "to": "0x563471854c90"
      }
    }, 
    {
      "type": "Feature",
      "geometry": {
        "type": "LineString",
        "coordinates": [[16.4750000000, 48.0250000000], [16.5000000000, 48.0000000000]]
      },
      "properties": {
        "dbg_lines": "S4,S2",
        "from": "0x563471850ab0",
        "id": "0x56347185b4a0",
        "lines": [
          {
            "color": "",
            "id": "S4",
            "label": "S4"
          }, 
          {
            "color": "",
            "id": "S2",
            "label": "S2"
          }],
        "to": "0x563471854e80"
      }
    }, 
    {
      "type": "Feature",
      "geometry": {
        "type": "LineString",
        "coordinates": [[16.4750000000, 48.0250000000], [16.4750000000, 48.0000000000]]
      },
      "properties": {
        "dbg_lines": "S3,S4",
        "from": "0x563471850ab0",
        "id": "0x56347185b5a0",
        "lines": [
          {
            "color": "",
            "id": "S3",
            "label": "S3"
          }, 
          {
            "color": "",
            "id": "S4",
            "label": "S4"
          }],
        "to": "0x5634718546c0"
      }
    }, 
    {
      "type": "Feature",
      "geometry": {
        "type": "LineString",
        "coordinates": [[16.5250000000, 47.8750000000], [16.5500000000, 47.9000000000]]
      },
      "properties": {
        "dbg_lines": "S2,S4",
        "from": "0x563471850ca0",
        "id": "0x56347185b7b0",
        "lines": [
          {
            "color": "",
            "id": "S2",
            "label": "S2"
          }, 
          {
            "color": "",
            "id": "S4",
            "label": "S4"
          }],
        "to": "0x563471851270"
      }
    }, 
    {
      "type": "Feature",
      "geometry": {
        "type": "LineString",
        "coordinates": [[16.5250000000, 47.8750000000], [16.5500000000, 47.8500000000]]
      },
      "properties": {
        "dbg_lines": "S4",
        "from": "0x563471850ca0",
        "id": "0x56347185ba60",
        "lines": [
          {
            "color": "",
            "id": "S4",
            "label": "S4"
          }],
        "to": "0x563471855e00"
      }
    }, 
    {
      "type": "Feature",
      "geometry": {
        "type": "LineString",
        "coordinates": [[16.5500000000, 48.1500000000], [16.5250000000, 48.1750000000]]
      },
      "properties": {
        "dbg_lines": "S3",
        "from": "0x563471850e90",
        "id": "0x56347185bbc0",
        "lines": [
          {
            "color": "",
            "id": "S3",
            "label": "S3"
          }],
        "to": "0x563471855260"
      }
    }, 
    {
      "type": "Feature",
      "geometry": {
        "type": "LineString",
        "coordinates": [[16.5500000000, 48.1500000000], [16.5750000000, 48.1250000000]]
      },
      "properties": {
        "dbg_lines": "S4,S3,S0",
        "from": "0x563471850e90",
        "id": "0x56347185bd20",
        "lines": [
          {
            "color": "",
            "id": "S4",
            "label": "S4"
          }, 
          {
            "color": "",
            "id": "S3",
            "label": "S3"
          }, 
          {
            "color": "",
            "id": "S0",
            "label": "S0"
          }],
        "to": "0x563471851460"
      }
    }, 
    {
      "type": "Feature",
      "geometry": {
        "type": "LineString",
        "coordinates": [[16.5500000000, 47.9250000000], [16.5500000000, 47.9500000000]]
      },
      "properties": {
        "dbg_lines": "S2,S4",
        "from": "0x563471851080",
        "id": "0x56347185c370",
        "lines": [
          {
            "color": "",
            "id": "S2",
            "label": "S2"
          }, 
          {
            "color": "",
            "id": "S4",
            "label": "S4"
          }],
        "to": "0x563471855c10"
      }
    }, 
    {
      "type": "Feature",
      "geometry": {
        "type": "LineString",
        "coordinates": [[16.5500000000, 47.9250000000], [16.5750000000, 47.9250000000]]
      },
      "properties": {
        "dbg_lines": "S4,S2",
        "from": "0x563471851080",
        "id": "0x56347185c4f0",
        "lines": [
          {
            "color": "",
            "id": "S4",
            "label": "S4"
          }, 
          {
            "color": "",
            "id": "S2",
            "label": "S2"
          }],
        "to": "0x563471851650"
      }
    }, 
    {
      "type": "Feature",
      "geometry": {
        "type": "LineString",
        "coordinates": [[16.5500000000, 47.9000000000], [16.5750000000, 47.9250000000]]
      },
      "properties": {
        "dbg_lines": "S2,S4",
        "from": "0x563471851270",
        "id": "0x56347185c710",
        "lines": [
          {
            "color": "",
            "id": "S2",
            "label": "S2"
          }, 
          {
            "color": "",
            "id": "S4",
            "label": "S4"
          }],
        "to": "0x563471851650"
      }
    }, 
    {
      "type": "Feature",
      "geometry": {
        "type": "LineString",
        "coordinates": [[16.5750000000, 48.1250000000], [16.6000000000, 48.1500000000]]
      },
      "properties": {
        "dbg_lines": "S0",
        "from": "0x563471851460",
        "id": "0x56347185c950",
        "lines": [
          {
            "color": "",
            "id": "S0",
            "label": "S0"
          }],
        "to": "0x5634718565c0"
      }
    }, 
    {
      "type": "Feature",
      "geometry": {
        "type": "LineString",
        "coordinates": [[16.5750000000, 48.1250000000], [16.6000000000, 48.1000000000]]
      },
      "properties": {
        "dbg_lines": "S4",
        "from": "0x563471851460",
        "id": "0x56347185cab0",
        "lines": [
          {
            "color": "",
            "id": "S4",
            "label": "S4"
          }],
        "to": "0x5634718567b0"
      }
    }, 
    {
      "type": "Feature",
      "geometry": {
        "type": "LineString",
        "coordinates": [[16.6250000000, 48.0500000000], [16.6000000000, 48.0500000000]]
      },
      "properties": {
        "dbg_lines": "S5",
        "from": "0x563471851840",
        "id": "0x56347185cbf0",
        "lines": [
          {
            "color": "",
            "id": "S5",
            "label": "S5"
          }],
        "to": "0x5634718569a0"
      }
    }, 
    {
      "type": "Feature",
      "geometry": {
        "type": "LineString",
        "coordinates": [[16.6250000000, 48.0500000000], [16.6000000000, 48.0250000000]]
      },
      "properties": {
        "dbg_lines": "S1",
        "from": "0x563471851840",
        "id": "0x56347185cd50",
        "lines": [
          {
            "color": "",
            "id": "S1",
            "label": "S1"
          }],
        "to": "0x563471856b90"
      }
    }, 
    {
      "type": "Feature",
      "geometry": {
        "type": "LineString",
        "coordinates": [[16.6250000000, 48.0500000000], [16.6250000000, 48.0750000000]]
      },
      "properties": {
        "dbg_lines": "S4",
        "from": "0x563471851840",
        "id": "0x56347185ce90",
        "lines": [
          {
            "color": "",
            "id": "S4",
            "label": "S4"
          }],
        "to": "0x563471857160"
      }
    }, 
    {
      "type": "Feature",
      "geometry": {
        "type": "LineString",
        "coordinates": [[16.6250000000, 48.0500000000], [16.6500000000, 48.0250000000]]
      },
      "properties": {
        "dbg_lines": "S4",
        "from": "0x563471851840",
        "id": "0x56347185cfd0",
        "lines": [
          {
            "color": "",
            "id": "S4",
            "label": "S4"
          }],
        "to": "0x563471857730"
      }
    }, 
    {
      "type": "Feature",
      "geometry": {
        "type": "LineString",
        "coordinates": [[16.6500000000, 47.9250000000], [16.6750000000, 47.9500000000]]
      },
      "properties": {
        "dbg_lines": "S4",
        "from": "0x563471851a30",
        "id": "0x56347185d0f0",
        "lines": [
          {
            "color": "",
            "id": "S4",
            "label": "S4"
          }],
        "to": "0x563471857b10"
      }
    }, 
    {
      "type": "Feature",
      "geometry": {
        "type": "LineString",
        "coordinates": [[16.6500000000, 47.9250000000], [16.6500000000, 47.9000000000]]
      },
      "properties": {
        "dbg_lines": "S4",
        "from": "0x563471851a30",
        "id": "0x56347185d250",
        "lines": [
          {
            "color": "",
            "id": "S4",
            "label": "S4"
          }],
        "to": "0x563471857d00"
      }
    }, 
    {
      "type": "Feature",
      "geometry": {
        "type": "LineString",
        "coordinates": [[16.6500000000, 47.8500000000], [16.6250000000, 47.8500000000]]
      },
      "properties": {
        "dbg_lines": "S4",
        "from": "0x563471851c20",
        "id": "0x56347185d390",
        "lines": [
          {
            "color": "",
            "id": "S4",
            "label": "S4"
          }],
        "to": "0x563471857350"
      }
    }, 
    {
      "type": "Feature",
      "geometry": {
        "type": "LineString",
        "coordinates": [[16.6500000000, 47.8500000000], [16.6500000000, 47.8750000000]]
      },
      "properties": {
        "dbg_lines": "S4",
        "from": "0x563471851c20",
        "id": "0x56347185d520",
        "lines": [
          {
            "color": "",
            "id": "S4",
            "label": "S4"
          }],
        "to": "0x563471857ef0"
      }
    }, 
    {
      "type": "Feature",
      "geometry": {
        "type": "LineString",
        "coordinates": [[16.6750000000, 48.1750000000], [16.6500000000, 48.1750000000]]
      },
      "properties": {
        "dbg_lines": "S0",
        "from": "0x563471851e10",
        "id": "0x56347185d690",
        "lines": [
          {
            "color": "",
            "id": "S0",
            "label": "S0"
          }],
        "to": "0x563471857540"
      }
    }, 
    {
      "type": "Feature",
      "geometry": {
        "type": "LineString",
        "coordinates": [[16.6750000000, 48.1750000000], [16.7000000000, 48.1750000000]]
      },
      "properties": {
        "dbg_lines": "S0",
        "from": "0x563471851e10",
        "id": "0x56347185d820",
        "lines": [
          {
            "color": "",
            "id": "S0",
            "label": "S0"
          }],
        "to": "0x563471852000"
      }
    }, 
    {
      "type": "Feature",
      "geometry": {
        "type": "LineString",
        "coordinates": [[16.7000000000, 47.9750000000], [16.6750000000, 48.0000000000]]
      },
      "properties": {
        "dbg_lines": "S4",
        "from": "0x5634718521f0",
        "id": "0x56347185d990",
        "lines": [
          {
            "color": "",
            "id": "S4",
            "label": "S4"
          }],
        "to": "0x563471857920"
      }
    }, 
    {
      "type": "Feature",
      "geometry": {
        "type": "LineString",
        "coordinates": [[16.7000000000, 47.9750000000], [16.6750000000, 47.9500000000]]
      },
      "properties": {
        "dbg_lines": "S4",
        "from": "0x5634718521f0",
        "id": "0x56347185db20",
        "lines": [
          {
            "color": "",
            "id": "S4",
            "label": "S4"
          }],
        "to": "0x563471857b10"
      }
    }, 
    {
      "type": "Feature",
      "geometry": {
        "type": "LineString",
        "coordinates": [[16.3250000000, 48.0750000000], [16.3250000000, 48.0500000000]]
      },
      "properties": {
        "dbg_lines": "S3",
        "from": "0x5634718523e0",
        "id": "0x56347185dcd0",
        "lines": [
          {
            "color": "",
            "id": "S3",
            "label": "S3"
          }],
        "to": "0x5634718525d0"
      }
    }, 
    {
      "type": "Feature",
      "geometry": {
        "type": "LineString",
        "coordinates": [[16.3250000000, 48.0500000000], [16.3250000000, 48.0250000000]]
      },
      "properties": {
        "dbg_lines": "S3",
        "from": "0x5634718525d0",
        "id": "0x56347185dea0",
        "lines": [
          {
            "color": "",
            "id": "S3",
            "label": "S3"
          }],
        "to": "0x5634718527c0"
      }
    }, 
    {
      "type": "Feature",
      "geometry": {
        "type": "LineString",
        "coordinates": [[16.3500000000, 48.0250000000], [16.3750000000, 48.0250000000]]
      },
      "properties": {
        "dbg_lines": "S3,S2",
        "from": "0x5634718529b0",
        "id": "0x56347185e050",
        "lines": [
          {
            "color": "",
            "id": "S3",
            "label": "S3"
          }, 
          {
            "color": "",
            "id": "S2",
            "label": "S2"
          }],
        "to": "0x563471852f80"
      }
    }, 
    {
      "type": "Feature",
      "geometry": {
        "type": "LineString",
        "coordinates": [[16.3750000000, 48.0750000000], [16.4000000000, 48.0500000000]]
      },
      "properties": {
        "dbg_lines": "S1",
        "from": "0x563471852d90",
        "id": "0x56347185e6d0",
        "lines": [
          {
            "color": "",
            "id": "S1",
            "label": "S1"
          }],
        "to": "0x563471853170"
      }
    }, 
    {
      "type": "Feature",
      "geometry": {
        "type": "LineString",
        "coordinates": [[16.3750000000, 48.0250000000], [16.4000000000, 48.0250000000]]
      },
      "properties": {
        "dbg_lines": "S3,S2",
        "from": "0x563471852f80",
        "id": "0x56347185e830",
        "lines": [
          {
            "color": "",
            "id": "S3",
            "label": "S3"
          }, 
          {
            "color": "",
            "id": "S2",
            "label": "S2"
          }],
        "to": "0x563471853360"
      }
    }, 
    {
      "type": "Feature",
      "geometry": {
        "type": "LineString",
        "coordinates": [[16.4000000000, 48.0500000000], [16.4250000000, 48.0250000000]]
      },
      "properties": {
        "dbg_lines": "S1",
        "from": "0x563471853170",
        "id": "0x56347185eaf0",
        "lines": [
          {
            "color": "",
            "id": "S1",
            "label": "S1"
          }],
        "to": "0x563471853b20"
      }
    }, 
    {
      "type": "Feature",
      "geometry": {
        "type": "LineString",
        "coordinates": [[16.4000000000, 48.0250000000], [16.4250000000, 48.0250000000]]
      },
      "properties": {
        "dbg_lines": "S3,S2",
        "from": "0x563471853360",
        "id": "0x56347185ec50",
        "lines": [
          {
            "color": "",
            "id": "S3",
            "label": "S3"
          }, 
          {
            "color": "",
            "id": "S2",
            "label": "S2"
          }],
        "to": "0x563471853b20"
      }
    }, 
    {
      "type": "Feature",
      "geometry": {
        "type": "LineString",
        "coordinates": [[16.4000000000, 47.8750000000], [16.4250000000, 47.9000000000]]
      },
      "properties": {
        "dbg_lines": "S5",
        "from": "0x563471853550",
        "id": "0x56347185eef0",
        "lines": [
          {
            "color": "",
            "id": "S5",
            "label": "S5"
          }],
        "to": "0x563471853d10"
      }
    }, 
    {
      "type": "Feature",
      "geometry": {
        "type": "LineString",
        "coordinates": [[16.4000000000, 48.1750000000], [16.4000000000, 48.1500000000]]
      },
      "properties": {
        "dbg_lines": "S3",
        "from": "0x563471853740",
        "id": "0x56347185f050",
        "lines": [
          {
            "color": "",
            "id": "S3",
            "label": "S3"
          }],
        "to": "0x563471853930"
      }
    }, 
    {
      "type": "Feature",
      "geometry": {
        "type": "LineString",
        "coordinates": [[16.4250000000, 48.0250000000], [16.4500000000, 48.0250000000]]
      },
      "properties": {
        "dbg_lines": "S3,S2,S1",
        "from": "0x563471853b20",
        "id": "0x56347185f170",
        "lines": [
          {
            "color": "",
            "id": "S3",
            "label": "S3"
          }, 
          {
            "color": "",
            "id": "S2",
            "label": "S2"
          }, 
          {
            "color": "",
            "id": "S1",
            "label": "S1"
          }],
        "to": "0x5634718540f0"
      }
    }, 
    {
      "type": "Feature",
      "geometry": {
        "type": "LineString",
        "coordinates": [[16.4250000000, 47.9000000000], [16.4500000000, 47.9250000000]]
      },
      "properties": {
        "dbg_lines": "S5",
        "from": "0x563471853d10",
        "id": "0x56347185f900",
        "lines": [
          {
            "color": "",
            "id": "S5",
            "label": "S5"
          }],
        "to": "0x5634718542e0"
      }
    }, 
    {
      "type": "Feature",
      "geometry": {
        "type": "LineString",
        "coordinates": [[16.4500000000, 48.2250000000], [16.4750000000, 48.2250000000]]
      },
      "properties": {
        "dbg_lines": "S3",
        "from": "0x563471853f00",
        "id": "0x56347185fa60",
        "lines": [
          {
            "color": "",
            "id": "S3",
            "label": "S3"
          }],
        "to": "0x5634718544d0"
      }
    }, 
    {
      "type": "Feature",
      "geometry": {
        "type": "LineString",
        "coordinates": [[16.4500000000, 47.9250000000], [16.4750000000, 47.9500000000]]
      },
      "properties": {
        "dbg_lines": "S5",
        "from": "0x5634718542e0",
        "id": "0x56347185fba0",
        "lines": [
          {
            "color": "",
            "id": "S5",
            "label": "S5"
          }],
        "to": "0x5634718548b0"
      }
    }, 
    {
      "type": "Feature",
      "geometry": {
        "type": "LineString",
        "coordinates": [[16.4750000000, 48.2250000000], [16.5000000000, 48.2000000000]]
      },
      "properties": {
        "dbg_lines": "S3",
        "from": "0x5634718544d0",
        "id": "0x56347185fce0",
        "lines": [
          {
            "color": "",
            "id": "S3",
            "label": "S3"
          }],
        "to": "0x563471854aa0"
      }
    }, 
    {
      "type": "Feature",
      "geometry": {
        "type": "LineString",
        "coordinates": [[16.4750000000, 47.9500000000], [16.5000000000, 47.9750000000]]
      },
      "properties": {
        "dbg_lines": "S5",
        "from": "0x5634718548b0",
        "id": "0x56347185fe20",
        "lines": [
          {
            "color": "",
            "id": "S5",
            "label": "S5"
          }],
        "to": "0x563471855070"
      }
    }, 
    {
      "type": "Feature",
      "geometry": {
        "type": "LineString",
        "coordinates": [[16.5000000000, 48.2000000000], [16.5250000000, 48.1750000000]]
      },
      "properties": {
        "dbg_lines": "S3",
        "from": "0x563471854aa0",
        "id": "0x56347185ff60",
        "lines": [
          {
            "color": "",
            "id": "S3",
            "label": "S3"
          }],
        "to": "0x563471855260"
      }
    }, 
    {
      "type": "Feature",
      "geometry": {
        "type": "LineString",
        "coordinates": [[16.5000000000, 48.0250000000], [16.5250000000, 48.0250000000]]
      },
      "properties": {
        "dbg_lines": "S1",
        "from": "0x563471854c90",
        "id": "0x563471860080",
        "lines": [
          {
            "color": "",
            "id": "S1",
            "label": "S1"
          }],
        "to": "0x563471855450"
      }
    }, 
    {
      "type": "Feature",
      "geometry": {
        "type": "LineString",
        "coordinates": [[16.5000000000, 48.0000000000], [16.5250000000, 47.9750000000]]
      },
      "properties": {
        "dbg_lines": "S4,S2",
        "from": "0x563471854e80",
        "id": "0x5634718601c0",
        "lines": [
          {
            "color": "",
            "id": "S4",
            "label": "S4"
          }, 
          {
            "color": "",
            "id": "S2",
            "label": "S2"
          }],
        "to": "0x563471855640"
      }
    }, 
    {
      "type": "Feature",
      "geometry": {
        "type": "LineString",
        "coordinates": [[16.5000000000, 47.9750000000], [16.5250000000, 48.0000000000]]
      },
      "properties": {
        "dbg_lines": "S5",
        "from": "0x563471855070",
        "id": "0x563471860450",
        "lines": [
          {
            "color": "",
            "id": "S5",
            "label": "S5"
          }],
        "to": "0x563471855830"
      }
    }, 
    {
      "type": "Feature",
      "geometry": {
        "type": "LineString",
        "coordinates": [[16.5250000000, 48.0250000000], [16.5500000000, 48.0250000000]]
      },
      "properties": {
        "dbg_lines": "S1",
        "from": "0x563471855450",
        "id": "0x5634718605b0",
        "lines": [
          {
            "color": "",
            "id": "S1",
            "label": "S1"
          }],
        "to": "0x563471855a20"
      }
    }, 
    {
      "type": "Feature",
      "geometry": {
        "type": "LineString",
        "coordinates": [[16.5250000000, 47.9750000000], [16.5500000000, 47.9500000000]]
      },
      "properties": {
        "dbg_lines": "S4,S2",
        "from": "0x563471855640",
        "id": "0x5634718606f0",
        "lines": [
          {
            "color": "",
            "id": "S4",
            "label": "S4"
          }, 
          {
            "color": "",
            "id": "S2",
            "label": "S2"
          }],
        "to": "0x563471855c10"
      }
    }, 
    {
      "type": "Feature",
      "geometry": {
        "type": "LineString",
        "coordinates": [[16.5250000000, 48.0000000000], [16.5500000000, 48.0250000000]]
      },
      "properties": {
        "dbg_lines": "S5",
        "from": "0x563471855830",
        "id": "0x563471860a20",
        "lines": [
          {
            "color": "",
            "id": "S5",
            "label": "S5"
          }],
        "to": "0x563471855a20"
      }
    }, 
    {
      "type": "Feature",
      "geometry": {
        "type": "LineString",
        "coordinates": [[16.5500000000, 48.0250000000], [16.5750000000, 48.0500000000]]
      },
      "properties": {
        "dbg_lines": "S5",
        "from": "0x563471855a20",
        "id": "0x563471860b60",
        "lines": [
          {
            "color": "",
            "id": "S5",
            "label": "S5"
          }],
        "to": "0x563471855ff0"
      }
    }, 
    {
      "type": "Feature",
      "geometry": {
        "type": "LineString",
        "coordinates": [[16.5500000000, 48.0250000000], [16.5750000000, 48.0250000000]]
      },
      "properties": {
        "dbg_lines": "S1",
        "from": "0x563471855a20",
        "id": "0x563471860ca0",
        "lines": [
          {
            "color": "",
            "id": "S1",
            "label": "S1"
          }],
        "to": "0x5634718561e0"
      }
    }, 
    {
      "type": "Feature",
      "geometry": {
        "type": "LineString",
        "coordinates": [[16.5500000000, 47.8500000000], [16.5750000000, 47.8500000000]]
      },
      "properties": {
        "dbg_lines": "S4",
        "from": "0x563471855e00",
        "id": "0x563471860dc0",
        "lines": [
          {
            "color": "",
            "id": "S4",
            "label": "S4"
          }],
        "to": "0x5634718563d0"
      }
    }, 
    {
      "type": "Feature",
      "geometry": {
        "type": "LineString",
        "coordinates": [[16.5750000000, 48.0500000000], [16.6000000000, 48.0500000000]]
      },
      "properties": {
        "dbg_lines": "S5",
        "from": "0x563471855ff0",
        "id": "0x563471860f00",
        "lines": [
          {
            "color": "",
            "id": "S5",
            "label": "S5"
          }],
        "to": "0x5634718569a0"
      }
    }, 
    {
      "type": "Feature",
      "geometry": {
        "type": "LineString",
        "coordinates": [[16.5750000000, 48.0250000000], [16.6000000000, 48.0250000000]]
      },
      "properties": {
        "dbg_lines": "S1",
        "from": "0x5634718561e0",
        "id": "0x563471861020",
        "lines": [
          {
            "color": "",
            "id": "S1",
            "label": "S1"
          }],
        "to": "0x563471856b90"
      }
    }, 
    {
      "type": "Feature",
      "geometry": {
        "type": "LineString",
        "coordinates": [[16.5750000000, 47.8500000000], [16.6000000000, 47.8500000000]]
      },
      "properties": {
        "dbg_lines": "S4",
        "from": "0x5634718563d0",
        "id": "0x563471861140",
        "lines": [
          {
            "color": "",
            "id": "S4",
            "label": "S4"
          }],
        "to": "0x563471856d80"
      }
    }, 
    {
      "type": "Feature",
      "geometry": {
        "type": "LineString",
        "coordinates": [[16.6000000000, 48.1500000000], [16.6250000000, 48.1750000000]]
      },
      "properties": {
        "dbg_lines": "S0",
        "from": "0x5634718565c0",
        "id": "0x563471861280",
        "lines": [
          {
            "color": "",
            "id": "S0",
            "label": "S0"
          }],
        "to": "0x563471856f70"
      }
    }, 
    {
      "type": "Feature",
      "geometry": {
        "type": "LineString",
        "coordinates": [[16.6000000000, 48.1000000000], [16.6250000000, 48.0750000000]]
      },
      "properties": {
        "dbg_lines": "S4",
        "from": "0x5634718567b0",
        "id": "0x563471861420",
        "lines": [
          {
            "color": "",
            "id": "S4",
            "label": "S4"
          }],
        "to": "0x563471857160"
      }
    }, 
    {
      "type": "Feature",
      "geometry": {
        "type": "LineString",
        "coordinates": [[16.6000000000, 47.8500000000], [16.6250000000, 47.8500000000]]
      },
      "properties": {
        "dbg_lines": "S4",
        "from": "0x563471856d80",
        "id": "0x5634718615d0",
        "lines": [
          {
            "color": "",
            "id": "S4",
            "label": "S4"
          }],
        "to": "0x563471857350"
      }
    }, 
    {
      "type": "Feature",
      "geometry": {
        "type": "LineString",
        "coordinates": [[16.6250000000, 48.1750000000], [16.6500000000, 48.1750000000]]
      },
      "properties": {
        "dbg_lines": "S0",
        "from": "0x563471856f70",
        "id": "0x563471861780",
        "lines": [
          {
            "color": "",
            "id": "S0",
            "label": "S0"
          }],
        "to": "0x563471857540"
      }
    }, 
    {
      "type": "Feature",
      "geometry": {
        "type": "LineString",
        "coordinates": [[16.6500000000, 48.0250000000], [16.6750000000, 48.0000000000]]
      },
      "properties": {
        "dbg_lines": "S4",
        "from": "0x563471857730",
        "id": "0x563471861930",
        "lines": [
          {
            "color": "",
            "id": "S4",
            "label": "S4"
          }],
        "to": "0x563471857920"
      }
    }, 
    {
      "type": "Feature",
      "geometry": {
        "type": "LineString",
        "coordinates": [[16.6500000000, 47.9000000000], [16.6500000000, 47.8750000000]]
      },
      "properties": {
        "dbg_lines": "S4",
        "from": "0x563471857d00",
        "id": "0x563471861ae0",
        "lines": [
          {
            "color": "",
            "id": "S4",
            "label": "S4"
          }],
        "to": "0x563471857ef0"
      }
    }]
}