{
  "type": "FeatureCollection",
  "properties": {
  },
  "features": [
    {
      "type": "Feature",
      "geometry": {
        "type": "Point",
        "coordinates": [16.3250000000, 48.0500000000]
      },
      "properties": {
        "deg": "1",
        "deg_in": "1",
        "deg_out": "1",
        "id": "0x55ab30c0e250",
        "station_id": "(1, 8)",
        "station_label": "(1, 8)"
      }
    }, 
    {
      "type": "Feature",
      "geometry": {
        "type": "Point",
        "coordinates": [16.4000000000, 47.9750000000]
      },
      "properties": {
        "deg": "2",
        "deg_in": "2",
        "deg_out": "2",
        "id": "0x55ab30c5c9a0",
        "station_id": "(4, 11)",
        "station_label": "(4, 11)"
      }
    }, 
    {
      "type": "Feature",
      "geometry": {
        "type": "Point",
        "coordinates": [16.4500000000, 48.2250000000]
      },
      "properties": {
        "deg": "1",
        "deg_in": "1",
        "deg_out": "1",
        "id": "0x55ab30c5cb90",
        "station_id": "(6, 1)",
        "station_label": "(6, 1)"
      }
    }, 
    {
      "type": "Feature",
      "geometry": {
        "type": "Point",
        "coordinates": [16.4500000000, 48.2000000000]
      },
      "properties": {
        "deg": "2",
        "deg_in": "2",
        "deg_out": "2",
        "id": "0x55ab30c5cd80",
        "station_id": "(6, 2)",
        "station_label": "(6, 2)"
      }
    }, 
    {
      "type": "Feature",
      "geometry": {
        "type": "Point",
        "coordinates": [16.4750000000, 47.8750000000]
      },
      "properties": {
        "deg": "2",
        "deg_in": "2",
        "deg_out": "2",
        "id": "0x55ab30c5cf70",
        "station_id": "(7, 15)",
        "station_label": "(7, 15)"
      }
    }, 
    {
      "type": "Feature",
      "geometry": {
        "type": "Point",
        "coordinates": [16.4750000000, 47.8500000000]
      },
      "properties": {
        "deg": "1",
        "deg_in": "1",
        "deg_out": "1",
        "id": "0x55ab30c5d160",
        "station_id": "(7, 16)",
        "station_label": "(7, 16)"
      }
    }, 
    {
      "type": "Feature",
      "geometry": {
        "type": "Point",
        "coordinates": [16.5000000000, 47.8750000000]
      },
      "properties": {
        "deg": "2",
        "deg_in": "2",
        "deg_out": "2",
        "id": "0x55ab30c5d350",
        "station_id": "(8, 15)",
        "station_label": "(8, 15)"
      }
    }, 
    {
      "type": "Feature",
      "geometry": {
        "type": "Point",
        "coordinates": [16.5250000000, 47.8500000000]
      },
      "properties": {
        "deg": "2",
        "deg_in": "2",
        "deg_out": "2",
        "id": "0x55ab30c5d540",
        "station_id": "(9, 16)",
        "station_label": "(9, 16)"
      }
    }, 
    {
      "type": "Feature",
      "geometry": {
        "type": "Point",
        "coordinates": [16.5500000000, 48.0750000000]
      },
      "properties": {
        "deg": "2",
        "deg_in": "2",
        "deg_out": "2",
        "id": "0x55ab30c5d730",
        "station_id": "(10, 7)",
        "station_label": "(10, 7)"
      }
    }, 
    {
      "type": "Feature",
      "geometry": {
        "type": "Point",
        "coordinates": [16.5500000000, 48.0500000000]
      },
      "properties": {
        "deg": "2",
        "deg_in": "2",
        "deg_out": "2",
        "id": "0x55ab30c5d920",
        "station_id": "(10, 8)",
        "station_label": "(10, 8)"
      }
    }, 
    {
      "type": "Feature",
      "geometry": {
        "type": "Point",
        "coordinates": [16.5500000000, 47.8750000000]
      },
      "properties": {
        "deg": "2",
        "deg_in": "2",
        "deg_out": "2",
        "id": "0x55ab30c5db10",
        "station_id": "(10, 15)",
        "station_label": "(10, 15)"
      }
    }, 
    {
      "type": "Feature",
      "geometry": {
        "type": "Point",
        "coordinates": [16.5500000000, 47.8500000000]
      },
      "properties": {
        "deg": "3",
        "deg_in": "3",
        "deg_out": "3",
        "id": "0x55ab30c5dd00",
        "station_id": "(10, 16)",
        "station_label": "(10, 16)"
      }
    }, 
    {
      "type": "Feature",
      "geometry": {
        "type": "Point",
        "coordinates": [16.5750000000, 48.0250000000]
      },
      "properties": {
        "deg": "2",
        "deg_in": "2",
        "deg_out": "2",
        "id": "0x55ab30c5def0",
        "station_id": "(11, 9)",
        "station_label": "(11, 9)"
      }
    }, 
    {
      "type": "Feature",
      "geometry": {
        "type": "Point",
        "coordinates": [16.5750000000, 47.8500000000]
      },
      "properties": {
        "deg": "1",
        "deg_in": "1",
        "deg_out": "1",
        "id": "0x55ab30c5e0e0",
        "station_id": "(11, 16)",
        "station_label": "(11, 16)"
      }
    }, 
    {
      "type": "Feature",
      "geometry": {
        "type": "Point",
        "coordinates": [16.6000000000, 47.9500000000]
      },
      "properties": {
        "deg": "5",
        "deg_in": "5",
        "deg_out": "5",
        "id": "0x55ab30c5e2d0",
        "station_id": "(12, 12)",
        "station_label": "(12, 12)"
      }
    }, 
    {
      "type": "Feature",
      "geometry": {
        "type": "Point",
        "coordinates": [16.6250000000, 48.1750000000]
      },
      "properties": {
        "deg": "2",
        "deg_in": "2",
        "deg_out": "2",
        "id": "0x55ab30c5e4c0",
        "station_id": "(13, 3)",
        "station_label": "(13, 3)"
      }
    }, 
    {
      "type": "Feature",
      "geometry": {
        "type": "Point",
        "coordinates": [16.6750000000, 48.1250000000]
      },
      "properties": {
        "deg": "2",
        "deg_in": "2",
        "deg_out": "2",
        "id": "0x55ab30c5e6b0",
        "station_id": "(15, 5)",
        "station_label": "(15, 5)"
      }
    }, 
    {
      "type": "Feature",
      "geometry": {
        "type": "Point",
        "coordinates": [16.7000000000, 48.1250000000]
      },
      "properties": {
        "deg": "2",
        "deg_in": "2",
        "deg_out": "2",
        "id": "0x55ab30c5e8a0",
        "station_id": "(16, 5)",
        "station_label": "(16, 5)"
      }
    }, 
    {
      "type": "Feature",
      "geometry": {
        "type": "Point",
        "coordinates": [16.7000000000, 48.1000000000]
      },
      "properties": {
        "deg": "1",
        "deg_in": "1",
        "deg_out": "1",
        "id": "0x55ab30c5ea90",
        "station_id": "(16, 6)",
        "station_label": "(16, 6)"
      }
    }, 
    {
      "type": "Feature",
      "geometry": {
        "type": "Point",
        "coordinates": [16.7000000000, 47.9750000000]
      },
      "properties": {
        "deg": "1",
        "deg_in": "1",
        "deg_out": "1",
        "id": "0x55ab30c5ec80",
        "station_id": "(16, 11)",
        "station_label": "(16, 11)"
      }
    }, 
    {
      "type": "Feature",
      "geometry": {
        "type": "Point",
        "coordinates": [16.3500000000, 48.0250000000]
      },
      "properties": {
        "deg": "2",
        "deg_in": "2",
        "deg_out": "2",
        "id": "0x55ab30c5ee70",
        "station_id": "(2, 9)",
        "station_label": "(2, 9)"
      }
    }, 
    {
      "type": "Feature",
      "geometry": {
        "type": "Point",
        "coordinates": [16.3750000000, 48.0000000000]
      },
      "properties": {
        "deg": "2",
        "deg_in": "2",
        "deg_out": "2",
        "id": "0x55ab30c5f060",
        "station_id": "(3, 10)",
        "station_label": "(3, 10)"
      }
    }, 
    {
      "type": "Feature",
      "geometry": {
        "type": "Point",
        "coordinates": [16.4250000000, 47.9750000000]
      },
      "properties": {
        "deg": "2",
        "deg_in": "2",
        "deg_out": "2",
        "id": "0x55ab30c5f250",
        "station_id": "(5, 11)",
        "station_label": "(5, 11)"
      }
    }, 
    {
      "type": "Feature",
      "geometry": {
        "type": "Point",
        "coordinates": [16.4500000000, 47.9750000000]
      },
      "properties": {
        "deg": "2",
        "deg_in": "2",
        "deg_out": "2",
        "id": "0x55ab30c5f440",
        "station_id": "(6, 11)",
        "station_label": "(6, 11)"
      }
    }, 
    {
      "type": "Feature",
      "geometry": {
        "type": "Point",
        "coordinates": [16.4750000000, 48.1750000000]
      },
      "properties": {
        "deg": "2",
        "deg_in": "2",
        "deg_out": "2",
        "id": "0x55ab30c5f630",
        "station_id": "(7, 3)",
        "station_label": "(7, 3)"
      }
    }, 
    {
      "type": "Feature",
      "geometry": {
        "type": "Point",
        "coordinates": [16.4750000000, 47.9750000000]
      },
      "properties": {
        "deg": "2",
        "deg_in": "2",
        "deg_out": "2",
        "id": "0x55ab30c5f820",
        "station_id": "(7, 11)",
        "station_label": "(7, 11)"
      }
    }, 
    {
      "type": "Feature",
      "geometry": {
        "type": "Point",
        "coordinates": [16.5000000000, 48.1500000000]
      },
      "properties": {
        "deg": "2",
        "deg_in": "2",
        "deg_out": "2",
        "id": "0x55ab30c5fa10",
        "station_id": "(8, 4)",
        "station_label": "(8, 4)"
      }
    }, 
    {
      "type": "Feature",
      "geometry": {
        "type": "Point",
        "coordinates": [16.5000000000, 47.9750000000]
      },
      "properties": {
        "deg": "2",
        "deg_in": "2",
        "deg_out": "2",
        "id": "0x55ab30c5fc00",
        "station_id": "(8, 11)",
        "station_label": "(8, 11)"
      }
    }, 
    {
      "type": "Feature",
      "geometry": {
        "type": "Point",
        "coordinates": [16.5250000000, 48.1250000000]
      },
      "properties": {
        "deg": "2",
        "deg_in": "2",
        "deg_out": "2",
        "id": "0x55ab30c5fdf0",
        "station_id": "(9, 5)",
        "station_label": "(9, 5)"
      }
    }, 
    {
      "type": "Feature",
      "geometry": {
        "type": "Point",
        "coordinates": [16.5250000000, 47.9750000000]
      },
      "properties": {
        "deg": "2",
        "deg_in": "2",
        "deg_out": "2",
        "id": "0x55ab30c5ffe0",
        "station_id": "(9, 11)",
        "station_label": "(9, 11)"
      }
    }, 
    {
      "type": "Feature",
      "geometry": {
        "type": "Point",
        "coordinates": [16.5500000000, 48.1000000000]
      },
      "properties": {
        "deg": "2",
        "deg_in": "2",
        "deg_out": "2",
        "id": "0x55ab30c601d0",
        "station_id": "(10, 6)",
        "station_label": "(10, 6)"
      }
    }, 
    {
      "type": "Feature",
      "geometry": {
        "type": "Point",
        "coordinates": [16.5500000000, 47.9750000000]
      },
      "properties": {
        "deg": "2",
        "deg_in": "2",
        "deg_out": "2",
        "id": "0x55ab30c603c0",
        "station_id": "(10, 11)",
        "station_label": "(10, 11)"
      }
    }, 
    {
      "type": "Feature",
      "geometry": {
        "type": "Point",
        "coordinates": [16.5750000000, 47.9750000000]
      },
      "properties": {
        "deg": "2",
        "deg_in": "2",
        "deg_out": "2",
        "id": "0x55ab30c605b0",
        "station_id": "(11, 11)",
        "station_label": "(11, 11)"
      }
    }, 
    {
      "type": "Feature",
      "geometry": {
        "type": "Point",
        "coordinates": [16.5500000000, 47.9000000000]
      },
      "properties": {
        "deg": "2",
        "deg_in": "2",
        "deg_out": "2",
        "id": "0x55ab30c607a0",
        "station_id": "(10, 14)",
        "station_label": "(10, 14)"
      }
    }, 
    {
      "type": "Feature",
      "geometry": {
        "type": "Point",
        "coordinates": [16.5750000000, 47.9250000000]
      },
      "properties": {
        "deg": "2",
        "deg_in": "2",
        "deg_out": "2",
        "id": "0x55ab30c60990",
        "station_id": "(11, 13)",
        "station_label": "(11, 13)"
      }
    }, 
    {
      "type": "Feature",
      "geometry": {
        "type": "Point",
        "coordinates": [16.6000000000, 48.0000000000]
      },
      "properties": {
        "deg": "2",
        "deg_in": "2",
        "deg_out": "2",
        "id": "0x55ab30c60b80",
        "station_id": "(12, 10)",
        "station_label": "(12, 10)"
      }
    }, 
    {
      "type": "Feature",
      "geometry": {
        "type": "Point",
        "coordinates": [16.6000000000, 47.9750000000]
      },
      "properties": {
        "deg": "2",
        "deg_in": "2",
        "deg_out": "2",
        "id": "0x55ab30c60d70",
        "station_id": "(12, 11)",
        "station_label": "(12, 11)"
      }
    }, 
    {
      "type": "Feature",
      "geometry": {
        "type": "Point",
        "coordinates": [16.6250000000, 47.9750000000]
      },
      "properties": {
        "deg": "2",
        "deg_in": "2",
        "deg_out": "2",
        "id": "0x55ab30c60f60",
        "station_id": "(13, 11)",
        "station_label": "(13, 11)"
      }
    }, 
    {
      "type": "Feature",
      "geometry": {
        "type": "Point",
        "coordinates": [16.6250000000, 47.9500000000]
      },
      "properties": {
        "deg": "2",
        "deg_in": "2",
        "deg_out": "2",
        "id": "0x55ab30c61150",
        "station_id": "(13, 12)",
        "station_label": "(13, 12)"
      }
    }, 
    {
      "type": "Feature",
      "geometry": {
        "type": "Point",
        "coordinates": [16.6500000000, 48.1500000000]
      },
      "properties": {
        "deg": "2",
        "deg_in": "2",
        "deg_out": "2",
        "id": "0x55ab30c61340",
        "station_id": "(14, 4)",
        "station_label": "(14, 4)"
      }
    }, 
    {
      "type": "Feature",
      "geometry": {
        "type": "Point",
        "coordinates": [16.6250000000, 48.1500000000]
      },
      "properties": {
        "deg": "2",
        "deg_in": "2",
        "deg_out": "2",
        "id": "0x55ab30c61530",
        "station_id": "(13, 4)",
        "station_label": "(13, 4)"
      }
    }, 
    {
      "type": "Feature",
      "geometry": {
        "type": "Point",
        "coordinates": [16.6250000000, 48.1250000000]
      },
      "properties": {
        "deg": "2",
        "deg_in": "2",
        "deg_out": "2",
        "id": "0x55ab30c61720",
        "station_id": "(13, 5)",
        "station_label": "(13, 5)"
      }
    }, 
    {
      "type": "Feature",
      "geometry": {
        "type": "Point",
        "coordinates": [16.6250000000, 48.1000000000]
      },
      "properties": {
        "deg": "2",
        "deg_in": "2",
        "deg_out": "2",
        "id": "0x55ab30c61910",
        "station_id": "(13, 6)",
        "station_label": "(13, 6)"
      }
    }, 
    {
      "type": "Feature",
      "geometry": {
        "type": "Point",
        "coordinates": [16.6250000000, 48.0750000000]
      },
      "properties": {
        "deg": "2",
        "deg_in": "2",
        "deg_out": "2",
        "id": "0x55ab30c61b00",
        "station_id": "(13, 7)",
        "station_label": "(13, 7)"
      }
    }, 
    {
      "type": "Feature",
      "geometry": {
        "type": "Point",
        "coordinates": [16.6250000000, 48.0500000000]
      },
      "properties": {
        "deg": "2",
        "deg_in": "2",
        "deg_out": "2",
        "id": "0x55ab30c61cf0",
        "station_id": "(13, 8)",
        "station_label": "(13, 8)"
      }
    }, 
    {
      "type": "Feature",
      "geometry": {
        "type": "Point",
        "coordinates": [16.6250000000, 48.0250000000]
      },
      "properties": {
        "deg": "2",
        "deg_in": "2",
        "deg_out": "2",
        "id": "0x55ab30c61ee0",
        "station_id": "(13, 9)",
        "station_label": "(13, 9)"
      }
    }, 
    {
      "type": "Feature",
      "geometry": {
        "type": "Point",
        "coordinates": [16.6250000000, 48.0000000000]
      },
      "properties": {
        "deg": "2",
        "deg_in": "2",
        "deg_out": "2",
        "id": "0x55ab30c620d0",
        "station_id": "(13, 10)",
        "station_label": "(13, 10)"
      }
    }, 
    {
      "type": "Feature",
      "geometry": {
        "type": "Point",
        "coordinates": [16.6500000000, 47.9500000000]
      },
      "properties": {
        "deg": "2",
        "deg_in": "2",
        "deg_out": "2",
        "id": "0x55ab30c622c0",
        "station_id": "(14, 12)",
        "station_label": "(14, 12)"
      }
    }, 
    {
      "type": "Feature",
      "geometry": {
        "type": "Point",
        "coordinates": [16.6750000000, 47.9500000000]
      },
      "properties": {
        "deg": "2",
        "deg_in": "2",
        "deg_out": "2",
        "id": "0x55ab30c624b0",
        "station_id": "(15, 12)",
        "station_label": "(15, 12)"
      }
    }, 
    {
      "type": "Feature",
      "geometry": {
        "type": "LineString",
        "coordinates": [[16.3250000000, 48.0500000000], [16.3500000000, 48.0250000000]]
      },
      "properties": {
        "dbg_lines": "S5",
        "from": "0x55ab30c0e250",
        "id": "0x55ab30c0cdc0",
        "lines": [
          {
            "color": "",
            "id": "S5",
            "label": "S5"
          }],
        "to": "0x55ab30c5ee70"
      }
    }, 
    {
      "type": "Feature",
      "geometry": {
        "type": "LineString",
        "coordinates": [[16.4000000000, 47.9750000000], [16.3750000000, 48.0000000000]]
      },
      "properties": {
        "dbg_lines": "S5",
        "from": "0x55ab30c5c9a0",
        "id": "0x55ab30c63360",
        "lines": [
          {
            "color": "",
            "id": "S5",
            "label": "S5"
          }],
        "to": "0x55ab30c5f060"
      }
    }, 
    {
      "type": "Feature",
      "geometry": {
        "type": "LineString",
        "coordinates": [[16.4000000000, 47.9750000000], [16.4250000000, 47.9750000000]]
      },
      "properties": {
        "dbg_lines": "S4,S1",
        "from": "0x55ab30c5c9a0",
        "id": "0x55ab30c63550",
        "lines": [
          {
            "color": "",
            "id": "S4",
            "label": "S4"
          }, 
          {
            "color": "",
            "id": "S1",
            "label": "S1"
          }],
        "to": "0x55ab30c5f250"
      }
    }, 
    {
      "type": "Feature",
      "geometry": {
        "type": "LineString",
        "coordinates": [[16.4500000000, 48.2250000000], [16.4500000000, 48.2000000000]]
      },
      "properties": {
        "dbg_lines": "S0",
        "from": "0x55ab30c5cb90",
        "id": "0x55ab30c63e00",
        "lines": [
          {
            "color": "",
            "id": "S0",
            "label": "S0"
          }],
        "to": "0x55ab30c5cd80"
      }
    }, 
    {
      "type": "Feature",
      "geometry": {
        "type": "LineString",
        "coordinates": [[16.4500000000, 48.2000000000], [16.4750000000, 48.1750000000]]
      },
      "properties": {
        "dbg_lines": "S0",
        "from": "0x55ab30c5cd80",
        "id": "0x55ab30c64040",
        "lines": [
          {
            "color": "",
            "id": "S0",
            "label": "S0"
          }],
        "to": "0x55ab30c5f630"
      }
    }, 
    {
      "type": "Feature",
      "geometry": {
        "type": "LineString",
        "coordinates": [[16.4750000000, 47.8750000000], [16.5000000000, 47.8750000000]]
      },
      "properties": {
        "dbg_lines": "S4",
        "from": "0x55ab30c5cf70",
        "id": "0x55ab30c64180",
        "lines": [
          {
            "color": "",
            "id": "S4",
            "label": "S4"
          }],
        "to": "0x55ab30c5d350"
      }
    }, 
    {
      "type": "Feature",
      "geometry": {
        "type": "LineString",
        "coordinates": [[16.4750000000, 47.8750000000], [16.4750000000, 47.8500000000]]
      },
      "properties": {
        "dbg_lines": "S4",
        "from": "0x55ab30c5cf70",
        "id": "0x55ab30c642e0",
        "lines": [
          {
            "color": "",
            "id": "S4",
            "label": "S4"
          }],
        "to": "0x55ab30c5d160"
      }
    }, 
    {
      "type": "Feature",
      "geometry": {
        "type": "LineString",
        "coordinates": [[16.5000000000, 47.8750000000], [16.5250000000, 47.8500000000]]
      },
      "properties": {
        "dbg_lines": "S4",
        "from": "0x55ab30c5d350",
        "id": "0x55ab30c64420",
        "lines": [
          {
            "color": "",
            "id": "S4",
            "label": "S4"
          }],
        "to": "0x55ab30c5d540"
      }
    }, 
    {
      "type": "Feature",
      "geometry": {
        "type": "LineString",
        "coordinates": [[16.5250000000, 47.8500000000], [16.5500000000, 47.8500000000]]
      },
      "properties": {
        "dbg_lines": "S4,S2",
        "from": "0x55ab30c5d540",
        "id": "0x55ab30c64560",
        "lines": [
          {
            "color": "",
            "id": "S4",
            "label": "S4"
          }, 
          {
            "color": "",
            "id": "S2",
            "label": "S2"
          }],
        "to": "0x55ab30c5dd00"
      }
    }, 
    {
      "type": "Feature",
      "geometry": {
        "type": "LineString",
        "coordinates": [[16.5500000000, 48.0750000000], [16.5500000000, 48.1000000000]]
      },
      "properties": {
        "dbg_lines": "S0",
        "from": "0x55ab30c5d730",
        "id": "0x55ab30c64b20",
        "lines": [
          {
            "color": "",
            "id": "S0",
            "label": "S0"
          }],
        "to": "0x55ab30c601d0"
      }
    }, 
    {
      "type": "Feature",
      "geometry": {
        "type": "LineString",
        "coordinates": [[16.5500000000, 48.0750000000], [16.5500000000, 48.0500000000]]
      },
      "properties": {
        "dbg_lines": "S0,S4,S3",
        "from": "0x55ab30c5d730",
        "id": "0x55ab30c64ce0",
        "lines": [
          {
            "color": "",
            "id": "S0",
            "label": "S0"
          }, 
          {
            "color": "",
            "id": "S4",
            "label": "S4"
          }, 
          {
            "color": "",
            "id": "S3",
            "label": "S3"
          }],
        "to": "0x55ab30c5d920"
      }
    }, 
    {
      "type": "Feature",
      "geometry": {
        "type": "LineString",
        "coordinates": [[16.5500000000, 48.0500000000], [16.5750000000, 48.0250000000]]
      },
      "properties": {
        "dbg_lines": "S4,S3",
        "from": "0x55ab30c5d920",
        "id": "0x55ab30c655c0",
        "lines": [
          {
            "color": "",
            "id": "S4",
            "label": "S4"
          }, 
          {
            "color": "",
            "id": "S3",
            "label": "S3"
          }],
        "to": "0x55ab30c5def0"
      }
    }, 
    {
      "type": "Feature",
      "geometry": {
        "type": "LineString",
        "coordinates": [[16.5500000000, 47.8750000000], [16.5500000000, 47.9000000000]]
      },
      "properties": {
        "dbg_lines": "S2,S4",
        "from": "0x55ab30c5db10",
        "id": "0x55ab30c65720",
        "lines": [
          {
            "color": "",
            "id": "S2",
            "label": "S2"
          }, 
          {
            "color": "",
            "id": "S4",
            "label": "S4"
          }],
        "to": "0x55ab30c607a0"
      }
    }, 
    {
      "type": "Feature",
      "geometry": {
        "type": "LineString",
        "coordinates": [[16.5500000000, 47.8750000000], [16.5500000000, 47.8500000000]]
      },
      "properties": {
        "dbg_lines": "S4,S2",
        "from": "0x55ab30c5db10",
        "id": "0x55ab30c65960",
        "lines": [
          {
            "color": "",
            "id": "S4",
            "label": "S4"
          }, 
          {
            "color": "",
            "id": "S2",
            "label": "S2"
          }],
        "to": "0x55ab30c5dd00"
      }
    }, 
    {
      "type": "Feature",
      "geometry": {
        "type": "LineString",
        "coordinates": [[16.5500000000, 47.8500000000], [16.5750000000, 47.8500000000]]
      },
      "properties": {
        "dbg_lines": "S4,S2",
        "from": "0x55ab30c5dd00",
        "id": "0x55ab30c65b60",
        "lines": [
          {
            "color": "",
            "id": "S4",
            "label": "S4"
          }, 
          {
            "color": "",
            "id": "S2",
            "label": "S2"
          }],
        "to": "0x55ab30c5e0e0"
      }
    }, 
    {
      "type": "Feature",
      "geometry": {
        "type": "LineString",
        "coordinates": [[16.5750000000, 48.0250000000], [16.6000000000, 48.0000000000]]
      },
      "properties": {
        "dbg_lines": "S4,S3",
        "from": "0x55ab30c5def0",
        "id": "0x55ab30c65db0",
        "lines": [
          {
            "color": "",
            "id": "S4",
            "label": "S4"
          }, 
          {
            "color": "",
            "id": "S3",
            "label": "S3"
          }],
        "to": "0x55ab30c60b80"
      }
    }, 
    {
      "type": "Feature",
      "geometry": {
        "type": "LineString",
        "coordinates": [[16.6000000000, 47.9500000000], [16.5750000000, 47.9750000000]]
      },
      "properties": {
        "dbg_lines": "S1,S4",
        "from": "0x55ab30c5e2d0",
        "id": "0x55ab30c66000",
        "lines": [
          {
            "color": "",
            "id": "S1",
            "label": "S1"
          }, 
          {
            "color": "",
            "id": "S4",
            "label": "S4"
          }],
        "to": "0x55ab30c605b0"
      }
    }, 
    {
      "type": "Feature",
      "geometry": {
        "type": "LineString",
        "coordinates": [[16.6000000000, 47.9500000000], [16.5750000000, 47.9250000000]]
      },
      "properties": {
        "dbg_lines": "S4,S2",
        "from": "0x55ab30c5e2d0",
        "id": "0x55ab30c66270",
        "lines": [
          {
            "color": "",
            "id": "S4",
            "label": "S4"
          }, 
          {
            "color": "",
            "id": "S2",
            "label": "S2"
          }],
        "to": "0x55ab30c60990"
      }
    }, 
    {
      "type": "Feature",
      "geometry": {
        "type": "LineString",
        "coordinates": [[16.6000000000, 47.9500000000], [16.6000000000, 47.9750000000]]
      },
      "properties": {
        "dbg_lines": "S3,S4",
        "from": "0x55ab30c5e2d0",
        "id": "0x55ab30c664c0",
        "lines": [
          {
            "color": "",
            "id": "S3",
            "label": "S3"
          }, 
          {
            "color": "",
            "id": "S4",
            "label": "S4"
          }],
        "to": "0x55ab30c60d70"
      }
    }, 
    {
      "type": "Feature",
      "geometry": {
        "type": "LineString",
        "coordinates": [[16.6000000000, 47.9500000000], [16.6250000000, 47.9750000000]]
      },
      "properties": {
        "dbg_lines": "S3,S1",
        "from": "0x55ab30c5e2d0",
        "id": "0x55ab30c66710",
        "lines": [
          {
            "color": "",
            "id": "S3",
            "label": "S3"
          }, 
          {
            "color": "",
            "id": "S1",
            "label": "S1"
          }],
        "to": "0x55ab30c60f60"
      }
    }, 
    {
      "type": "Feature",
      "geometry": {
        "type": "LineString",
        "coordinates": [[16.6000000000, 47.9500000000], [16.6250000000, 47.9500000000]]
      },
      "properties": {
        "dbg_lines": "S2,S3",
        "from": "0x55ab30c5e2d0",
        "id": "0x55ab30c66970",
        "lines": [
          {
            "color": "",
            "id": "S2",
            "label": "S2"
          }, 
          {
            "color": "",
            "id": "S3",
            "label": "S3"
          }],
        "to": "0x55ab30c61150"
      }
    }, 
    {
      "type": "Feature",
      "geometry": {
        "type": "LineString",
        "coordinates": [[16.6250000000, 48.1750000000], [16.6500000000, 48.1500000000]]
      },
      "properties": {
        "dbg_lines": "S3",
        "from": "0x55ab30c5e4c0",
        "id": "0x55ab30c66c00",
        "lines": [
          {
            "color": "",
            "id": "S3",
            "label": "S3"
          }],
        "to": "0x55ab30c61340"
      }
    }, 
    {
      "type": "Feature",
      "geometry": {
        "type": "LineString",
        "coordinates": [[16.6250000000, 48.1750000000], [16.6250000000, 48.1500000000]]
      },
      "properties": {
        "dbg_lines": "S1,S3",
        "from": "0x55ab30c5e4c0",
        "id": "0x55ab30c66d80",
        "lines": [
          {
            "color": "",
            "id": "S1",
            "label": "S1"
          }, 
          {
            "color": "",
            "id": "S3",
            "label": "S3"
          }],
        "to": "0x55ab30c61530"
      }
    }, 
    {
      "type": "Feature",
      "geometry": {
        "type": "LineString",
        "coordinates": [[16.6750000000, 48.1250000000], [16.6500000000, 48.1500000000]]
      },
      "properties": {
        "dbg_lines": "S3",
        "from": "0x55ab30c5e6b0",
        "id": "0x55ab30c66fe0",
        "lines": [
          {
            "color": "",
            "id": "S3",
            "label": "S3"
          }],
        "to": "0x55ab30c61340"
      }
    }, 
    {
      "type": "Feature",
      "geometry": {
        "type": "LineString",
        "coordinates": [[16.6750000000, 48.1250000000], [16.7000000000, 48.1250000000]]
      },
      "properties": {
        "dbg_lines": "S3",
        "from": "0x55ab30c5e6b0",
        "id": "0x55ab30c67140",
        "lines": [
          {
            "color": "",
            "id": "S3",
            "label": "S3"
          }],
        "to": "0x55ab30c5e8a0"
      }
    }, 
    {
      "type": "Feature",
      "geometry": {
        "type": "LineString",
        "coordinates": [[16.7000000000, 48.1250000000], [16.7000000000, 48.1000000000]]
      },
      "properties": {
        "dbg_lines": "S3",
        "from": "0x55ab30c5e8a0",
        "id": "0x55ab30c67280",
        "lines": [
          {
            "color": "",
            "id": "S3",
            "label": "S3"
          }],
        "to": "0x55ab30c5ea90"
      }
    }, 
    {
      "type": "Feature",
      "geometry": {
        "type": "LineString",
        "coordinates": [[16.7000000000, 47.9750000000], [16.6750000000, 47.9500000000]]
      },
      "properties": {
        "dbg_lines": "S3,S2",
        "from": "0x55ab30c5ec80",
        "id": "0x55ab30c673c0",
        "lines": [
          {
            "color": "",
            "id": "S3",
            "label": "S3"
          }, 
          {
            "color": "",
            "id": "S2",
            "label": "S2"
          }],
        "to": "0x55ab30c624b0"
      }
    }, 
    {
      "type": "Feature",
      "geometry": {
        "type": "LineString",
        "coordinates": [[16.3500000000, 48.0250000000], [16.3750000000, 48.0000000000]]
      },
      "properties": {
        "dbg_lines": "S5",
        "from": "0x55ab30c5ee70",
        "id": "0x55ab30c676a0",
        "lines": [
          {
            "color": "",
            "id": "S5",
            "label": "S5"
          }],
        "to": "0x55ab30c5f060"
      }
    }, 
    {
      "type": "Feature",
      "geometry": {
        "type": "LineString",
        "coordinates": [[16.4250000000, 47.9750000000], [16.4500000000, 47.9750000000]]
      },
      "properties": {
        "dbg_lines": "S4,S1",
        "from": "0x55ab30c5f250",
        "id": "0x55ab30c677e0",
        "lines": [
          {
            "color": "",
            "id": "S4",
            "label": "S4"
          }, 
          {
            "color": "",
            "id": "S1",
            "label": "S1"
          }],
        "to": "0x55ab30c5f440"
      }
    }, 
    {
      "type": "Feature",
      "geometry": {
        "type": "LineString",
        "coordinates": [[16.4500000000, 47.9750000000], [16.4750000000, 47.9750000000]]
      },
      "properties": {
        "dbg_lines": "S4,S1",
        "from": "0x55ab30c5f440",
        "id": "0x55ab30c67a00",
        "lines": [
          {
            "color": "",
            "id": "S4",
            "label": "S4"
          }, 
          {
            "color": "",
            "id": "S1",
            "label": "S1"
          }],
        "to": "0x55ab30c5f820"
      }
    }, 
    {
      "type": "Feature",
      "geometry": {
        "type": "LineString",
        "coordinates": [[16.4750000000, 48.1750000000], [16.5000000000, 48.1500000000]]
      },
      "properties": {
        "dbg_lines": "S0",
        "from": "0x55ab30c5f630",
        "id": "0x55ab30c67c90",
        "lines": [
          {
            "color": "",
            "id": "S0",
            "label": "S0"
          }],
        "to": "0x55ab30c5fa10"
      }
    }, 
    {
      "type": "Feature",
      "geometry": {
        "type": "LineString",
        "coordinates": [[16.4750000000, 47.9750000000], [16.5000000000, 47.9750000000]]
      },
      "properties": {
        "dbg_lines": "S4,S1",
        "from": "0x55ab30c5f820",
        "id": "0x55ab30c67df0",
        "lines": [
          {
            "color": "",
            "id": "S4",
            "label": "S4"
          }, 
          {
            "color": "",
            "id": "S1",
            "label": "S1"
          }],
        "to": "0x55ab30c5fc00"
      }
    }, 
    {
      "type": "Feature",
      "geometry": {
        "type": "LineString",
        "coordinates": [[16.5000000000, 48.1500000000], [16.5250000000, 48.1250000000]]
      },
      "properties": {
        "dbg_lines": "S0",
        "from": "0x55ab30c5fa10",
        "id": "0x55ab30c68050",
        "lines": [
          {
            "color": "",
            "id": "S0",
            "label": "S0"
          }],
        "to": "0x55ab30c5fdf0"
      }
    }, 
    {
      "type": "Feature",
      "geometry": {
        "type": "LineString",
        "coordinates": [[16.5000000000, 47.9750000000], [16.5250000000, 47.9750000000]]
      },
      "properties": {
        "dbg_lines": "S4,S1",
        "from": "0x55ab30c5fc00",
        "id": "0x55ab30c681b0",
        "lines": [
          {
            "color": "",
            "id": "S4",
            "label": "S4"
          }, 
          {
            "color": "",
            "id": "S1",
            "label": "S1"
          }],
        "to": "0x55ab30c5ffe0"
      }
    }, 
    {
      "type": "Feature",
      "geometry": {
        "type": "LineString",
        "coordinates": [[16.5250000000, 48.1250000000], [16.5500000000, 48.1000000000]]
      },
      "properties": {
        "dbg_lines": "S0",
        "from": "0x55ab30c5fdf0",
        "id": "0x55ab30c68470",
        "lines": [
          {
            "color": "",
            "id": "S0",
            "label": "S0"
          }],
        "to": "0x55ab30c601d0"
      }
    }, 
    {
      "type": "Feature",
      "geometry": {
        "type": "LineString",
        "coordinates": [[16.5250000000, 47.9750000000], [16.5500000000, 47.9750000000]]
      },
      "properties": {
        "dbg_lines": "S4,S1",
        "from": "0x55ab30c5ffe0",
        "id": "0x55ab30c685b0",
        "lines": [
          {
            "color": "",
            "id": "S4",
            "label": "S4"
          }, 
          {
            "color": "",
            "id": "S1",
            "label": "S1"
          }],
        "to": "0x55ab30c603c0"
      }
    }, 
    {
      "type": "Feature",
      "geometry": {
        "type": "LineString",
        "coordinates": [[16.5500000000, 47.9750000000], [16.5750000000, 47.9750000000]]
      },
      "properties": {
        "dbg_lines": "S4,S1",
        "from": "0x55ab30c603c0",
        "id": "0x55ab30c68830",
        "lines": [
          {
            "color": "",
            "id": "S4",
            "label": "S4"
          }, 
          {
            "color": "",
            "id": "S1",
            "label": "S1"
          }],
        "to": "0x55ab30c605b0"
      }
    }, 
    {
      "type": "Feature",
      "geometry": {
        "type": "LineString",
        "coordinates": [[16.5500000000, 47.9000000000], [16.5750000000, 47.9250000000]]
      },
      "properties": {
        "dbg_lines": "S2,S4",
        "from": "0x55ab30c607a0",
        "id": "0x55ab30c68a60",
        "lines": [
          {
            "color": "",
            "id": "S2",
            "label": "S2"
          }, 
          {
            "color": "",
            "id": "S4",
            "label": "S4"
          }],
        "to": "0x55ab30c60990"
      }
    }, 
    {
      "type": "Feature",
      "geometry": {
        "type": "LineString",
        "coordinates": [[16.6000000000, 48.0000000000], [16.6000000000, 47.9750000000]]
      },
      "properties": {
        "dbg_lines": "S4,S3",
        "from": "0x55ab30c60b80",
        "id": "0x55ab30c68c90",
        "lines": [
          {
            "color": "",
            "id": "S4",
            "label": "S4"
          }, 
          {
            "color": "",
            "id": "S3",
            "label": "S3"
          }],
        "to": "0x55ab30c60d70"
      }
    }, 
    {
      "type": "Feature",
      "geometry": {
        "type": "LineString",
        "coordinates": [[16.6250000000, 47.9750000000], [16.6250000000, 48.0000000000]]
      },
      "properties": {
        "dbg_lines": "S3,S1",
        "from": "0x55ab30c60f60",
        "id": "0x55ab30c68ec0",
        "lines": [
          {
            "color": "",
            "id": "S3",
            "label": "S3"
          }, 
          {
            "color": "",
            "id": "S1",
            "label": "S1"
          }],
        "to": "0x55ab30c620d0"
      }
    }, 
    {
      "type": "Feature",
      "geometry": {
        "type": "LineString",
        "coordinates": [[16.6250000000, 47.9500000000], [16.6500000000, 47.9500000000]]
      },
      "properties": {
        "dbg_lines": "S2,S3",
        "from": "0x55ab30c61150",
        "id": "0x55ab30c69110",
        "lines": [
          {
            "color": "",
            "id": "S2",
            "label": "S2"
          }, 
          {
            "color": "",
            "id": "S3",
            "label": "S3"
          }],
        "to": "0x55ab30c622c0"
      }
    }, 
    {
      "type": "Feature",
      "geometry": {
        "type": "LineString",
        "coordinates": [[16.6250000000, 48.1500000000], [16.6250000000, 48.1250000000]]
      },
      "properties": {
        "dbg_lines": "S1,S3",
        "from": "0x55ab30c61530",
        "id": "0x55ab30c69360",
        "lines": [
          {
            "color": "",
            "id": "S1",
            "label": "S1"
          }, 
          {
            "color": "",
            "id": "S3",
            "label": "S3"
          }],
        "to": "0x55ab30c61720"
      }
    }, 
    {
      "type": "Feature",
      "geometry": {
        "type": "LineString",
        "coordinates": [[16.6250000000, 48.1250000000], [16.6250000000, 48.1000000000]]
      },
      "properties": {
        "dbg_lines": "S1,S3",
        "from": "0x55ab30c61720",
        "id": "0x55ab30c695b0",
        "lines": [
          {
            "color": "",
            "id": "S1",
            "label": "S1"
          }, 
          {
            "color": "",
            "id": "S3",
            "label": "S3"
          }],
        "to": "0x55ab30c61910"
      }
    }, 
    {
      "type": "Feature",
      "geometry": {
        "type": "LineString",
        "coordinates": [[16.6250000000, 48.1000000000], [16.6250000000, 48.0750000000]]
      },
      "properties": {
        "dbg_lines": "S1,S3",
        "from": "0x55ab30c61910",
        "id": "0x55ab30c69800",
        "lines": [
          {
            "color": "",
            "id": "S1",
            "label": "S1"
          }, 
          {
            "color": "",
            "id": "S3",
            "label": "S3"
          }],
        "to": "0x55ab30c61b00"
      }
    }, 
    {
      "type": "Feature",
      "geometry": {
        "type": "LineString",
        "coordinates": [[16.6250000000, 48.0750000000], [16.6250000000, 48.0500000000]]
      },
      "properties": {
        "dbg_lines": "S1,S3",
        "from": "0x55ab30c61b00",
        "id": "0x55ab30c69a50",
        "lines": [
          {
            "color": "",
            "id": "S1",
            "label": "S1"
          }, 
          {
            "color": "",
            "id": "S3",
            "label": "S3"
          }],
        "to": "0x55ab30c61cf0"
      }
    }, 
    {
      "type": "Feature",
      "geometry": {
        "type": "LineString",
        "coordinates": [[16.6250000000, 48.0500000000], [16.6250000000, 48.0250000000]]
      },
      "properties": {
        "dbg_lines": "S1,S3",
        "from": "0x55ab30c61cf0",
        "id": "0x55ab30c69ca0",
        "lines": [
          {
            "color": "",
            "id": "S1",
            "label": "S1"
          }, 
          {
            "color": "",
            "id": "S3",
            "label": "S3"
          }],
        "to": "0x55ab30c61ee0"
      }
    }, 
    {
      "type": "Feature",
      "geometry": {
        "type": "LineString",
        "coordinates": [[16.6250000000, 48.0250000000], [16.6250000000, 48.0000000000]]
      },
      "properties": {
        "dbg_lines": "S1,S3",
        "from": "0x55ab30c61ee0",
        "id": "0x55ab30c69ef0",
        "lines": [
          {
            "color": "",
            "id": "S1",
            "label": "S1"
          }, 
          {
            "color": "",
            "id": "S3",
            "label": "S3"
          }],
        "to": "0x55ab30c620d0"
      }
    }, 
    {
      "type": "Feature",
      "geometry": {
        "type": "LineString",
        "coordinates": [[16.6500000000, 47.9500000000], [16.6750000000, 47.9500000000]]
      },
      "properties": {
        "dbg_lines": "S2,S3",
        "from": "0x55ab30c622c0",
        "id": "0x55ab30c6a120",
        "lines": [
          {
            "color": "",
            "id": "S2",
            "label": "S2"
          }, 
          {
            "color": "",
            "id": "S3",
            "label": "S3"
          }],
        "to": "0x55ab30c624b0"
      }
    }]
}